CHANGES.txt
LICENSE.txt
MANIFEST.in
README.txt
setup.py
js/__init__.py
js.ace.egg-info/PKG-INFO
js.ace.egg-info/SOURCES.txt
js.ace.egg-info/dependency_links.txt
js.ace.egg-info/entry_points.txt
js.ace.egg-info/namespace_packages.txt
js.ace.egg-info/not-zip-safe
js.ace.egg-info/requires.txt
js.ace.egg-info/top_level.txt
js/ace/__init__.py
js/ace/test_ace.txt
js/ace/resources/ace.js
js/ace/resources/ext-beautify.js
js/ace/resources/ext-code_lens.js
js/ace/resources/ext-elastic_tabstops_lite.js
js/ace/resources/ext-emmet.js
js/ace/resources/ext-error_marker.js
js/ace/resources/ext-keybinding_menu.js
js/ace/resources/ext-language_tools.js
js/ace/resources/ext-linking.js
js/ace/resources/ext-modelist.js
js/ace/resources/ext-options.js
js/ace/resources/ext-prompt.js
js/ace/resources/ext-rtl.js
js/ace/resources/ext-searchbox.js
js/ace/resources/ext-settings_menu.js
js/ace/resources/ext-spellcheck.js
js/ace/resources/ext-split.js
js/ace/resources/ext-static_highlight.js
js/ace/resources/ext-statusbar.js
js/ace/resources/ext-textarea.js
js/ace/resources/ext-themelist.js
js/ace/resources/ext-whitespace.js
js/ace/resources/keybinding-emacs.js
js/ace/resources/keybinding-sublime.js
js/ace/resources/keybinding-vim.js
js/ace/resources/keybinding-vscode.js
js/ace/resources/mode-abap.js
js/ace/resources/mode-abc.js
js/ace/resources/mode-actionscript.js
js/ace/resources/mode-ada.js
js/ace/resources/mode-alda.js
js/ace/resources/mode-apache_conf.js
js/ace/resources/mode-apex.js
js/ace/resources/mode-applescript.js
js/ace/resources/mode-aql.js
js/ace/resources/mode-asciidoc.js
js/ace/resources/mode-asl.js
js/ace/resources/mode-assembly_x86.js
js/ace/resources/mode-autohotkey.js
js/ace/resources/mode-batchfile.js
js/ace/resources/mode-c9search.js
js/ace/resources/mode-c_cpp.js
js/ace/resources/mode-cirru.js
js/ace/resources/mode-clojure.js
js/ace/resources/mode-cobol.js
js/ace/resources/mode-coffee.js
js/ace/resources/mode-coldfusion.js
js/ace/resources/mode-crystal.js
js/ace/resources/mode-csharp.js
js/ace/resources/mode-csound_document.js
js/ace/resources/mode-csound_orchestra.js
js/ace/resources/mode-csound_score.js
js/ace/resources/mode-csp.js
js/ace/resources/mode-css.js
js/ace/resources/mode-curly.js
