Metadata-Version: 1.0
Name: js.ace
Version: 1.4.11
Summary: Fanstatic packaging of Ajax.org Cloud9 Editor
Home-page: UNKNOWN
Author: Fanstatic Developers
Author-email: fanstatic@googlegroups.com
License: BSD
Platform: UNKNOWN
